tests/__init__.py
tests/conftest.py
tests/create_nauru_test.py
tests/test_create_new_tables.py
tests/test_delete_links_and_nodes.py
tests/test_import_network.py
tests/test_import_political_subdivisions.py
tests/test_import_population.py
tests/test_model.py
tests/test_pop_by_sex_and_age.py
tests/test_population_file_address.py
tests/test_set_source.py
tests/data_retrieval/__init__.py
tests/data_retrieval/test_generic_tag.py
tests/data_retrieval/test_import_osm_data.py
tests/data_retrieval/test_microsoft_building_footprint.py
tests/data_retrieval/test_osm_load_data.py
tests/data_retrieval/test_set_bounding_box.py
tests/model_creation/__init__.py
tests/model_creation/test_create_control_totals_taz.py
tests/model_creation/test_create_geo_cross_walk.py
tests/model_creation/test_create_seeds.py
tests/model_creation/test_create_totals_meta.py
tests/model_creation/test_save_synthetic_households.py
tests/model_creation/test_save_synthetic_persons.py
tests/model_creation/test_set_thread_number.py
tests/model_creation/test_subprocess.py
tests/model_creation/test_unzip_seed_files.py
tests/model_creation/test_user_change_controls.py
tests/model_creation/test_user_change_geographies.py
tests/model_creation/test_user_change_settings.py
tests/model_creation/test_user_change_validation_parameters.py
tests/model_creation/test_user_import_new_seeds.py
tests/model_creation/test_user_import_new_totals.py
tests/model_creation/test_validate_controlled_vars.py
tests/model_creation/test_validate_non_controlled_vars.py
tests/model_creation/test_zone_builder.py
tradesman/__init__.py
tradesman/model.py
tradesman/data/__init__.py
tradesman/data/load_zones.py
tradesman/data/mask_raster.py
tradesman/data/population_file_address.py
tradesman/data/population_raster.py
tradesman/data/population/all_raster_pop_source.csv
tradesman/data_retrieval/__init__.py
tradesman/data_retrieval/country_main_area.py
tradesman/data_retrieval/get_all_subdivisions.py
tradesman/data_retrieval/import_amenities.py
tradesman-0.2.dist-info/METADATA
tradesman-0.2.dist-info/WHEEL
tradesman-0.2.dist-info/top_level.txt
tradesman-0.2.dist-info/zip-safe
tradesman-0.2.dist-info/RECORD
